Metadata-Version: 1.0
Name: Products.listen
Version: 0.7.0
Summary: listen is a mailing list product for Plone
Home-page: http://oss.openplans.org/listen
Author: Robert Marianski
Author-email: rmarianski at openplans.org
License: GPL
Platform: UNKNOWN
